{"preferredFilename":"Bad Iteration 10","validationEntity":{"analysedDataType":"datasource","dataSourceID":"36026F38-4019-4D1D-802B-B1B7EDC8D9F0","dataResult":{"createdDate":"2024-03-04T19:37:41Z","dataSourceID":"36026F38-4019-4D1D-802B-B1B7EDC8D9F0","classesCount":9,"itemsCount":18,"dataURL":"file:\/\/\/Users\/simone\/Documents\/Github\/capstone\/src\/Model\/Signs-V2\/eval-data\/","dataAnalysis":{"issues":[{"description":"9 classes found, including bathroom-2, please-2, how-are-you-2","severity":"debug"},{"severity":"warning","description":"Less than 100 total activity recording files found - add more to improve model validation"},{"description":"Smallest class is \"hello-2\" with 2 activity recording files","severity":"debug"},{"severity":"debug","description":"Largest class is \"bathroom-2\" with 2 activity recording files"},{"severity":"good","description":"6 features are selected"}],"classifierAnalysis":{"labelStats":{"bathroom-2":2,"how-are-you-2":2,"hurt-2":2,"thank-you-2":2,"deaf-2":2,"hospital-2":2,"hard-of-hearing-2":2,"hello-2":2,"please-2":2}},"summary":{"canUseValidation":0,"sampleCount":18,"classCount":9}}}},"modifiedDate":"2024-03-04T21:03:45Z","id":"BD8DB8CE-D751-442D-865C-1C02DFBFD6A2","trainingEntity":{"dataSourceID":"72F6BA12-E283-49A9-AE59-B059E1AC34C5","checkpointMetrics":{"10":{"createdDate":"2024-03-04T19:37:36Z","iteration":10,"metrics":{"validationAccuracy":0.6800000071525574,"validationLoss":0,"loss":0.03592666983604431,"accuracy":0.8492848873138428}}},"trainingAccuracy":0.9811242308331948,"resumableCheckpoint":{"checkpointURL":"file:\/\/\/Users\/simone\/Library\/Caches\/com.apple.dt.createml\/projects\/F94725CA-623E-4119-8056-4CFFB990C875845115d7072f729aadb86178db7cc96e350ca24c\/sessions\/checkpoint.sessions\/5B5047E9-1319-4A41-9E17-EFA6713EF8E5\/training-000000010.checkpoint","iteration":10,"createdDate":"2024-03-04T19:37:36Z"},"dataResult":{"classesCount":9,"dataAnalysis":{"classifierAnalysis":{"labelStats":{"hard-of-hearing-2":31,"deaf-2":29,"please-2":23,"bathroom-2":25,"how-are-you-2":27,"hospital-2":30,"hurt-2":29,"thank-you-2":31,"hello-2":24}},"summary":{"sampleCount":249,"classCount":9,"canUseValidation":1},"issues":[{"severity":"debug","description":"9 classes found, including thank-you-2, hard-of-hearing-2, hospital-2"},{"severity":"good","description":"249 activity recording files found, automatically creating validation set"},{"description":"Smallest class is \"please-2\" with 23 activity recording files","severity":"debug"},{"severity":"debug","description":"Largest class is \"thank-you-2\" with 31 activity recording files"},{"description":"6 features are selected","severity":"good"}]},"columnValues":["0.03, 0.02, 0.02, 0.01, 0.01…","0.10, 0.10, 0.11, 0.14, 0.17…","-0.07, -0.09, -0.11, -0.13, -0.17…","0.21, 0.18, 0.03, -0.22, -0.52…","-0.09, -0.15, -0.23, -0.34, -0.50…","-0.01, -0.06, -0.13, -0.20, -0.29…"],"columns":["accX","accY","accZ","gyroX","gyroY","gyroZ"],"columnTypes":["Double","Double","Double","Double","Double","Double"],"itemsCount":249,"dataSourceID":"72F6BA12-E283-49A9-AE59-B059E1AC34C5","createdDate":"2024-03-04T19:37:41Z","dataURL":"file:\/\/\/Users\/simone\/Documents\/Github\/capstone\/src\/Model\/Signs-V2\/train-data\/"},"validationResults":{"activityClassifier":{"statsByLabel":{"how-are-you-2":{"precisionRecall":{"success":{"recall":0,"precision":0}},"count":432},"please-2":{"count":221,"precisionRecall":{"success":{"precision":1,"recall":1}}},"hospital-2":{"precisionRecall":{"success":{"recall":0.34572490706319703,"precision":0.3795918367346939}},"count":269},"deaf-2":{"count":189,"precisionRecall":{"success":{"precision":0.48586118251928023,"recall":1}}},"bathroom-2":{"count":166,"precisionRecall":{"success":{"precision":1,"recall":1}}},"hurt-2":{"count":160,"precisionRecall":{"success":{"recall":1,"precision":0.47619047619047616}}},"hello-2":{"count":108,"precisionRecall":{"success":{"precision":1,"recall":1}}},"thank-you-2":{"count":145,"precisionRecall":{"success":{"precision":1,"recall":1}}},"hard-of-hearing-2":{"precisionRecall":{"success":{"recall":1,"precision":0.7241379310344828}},"count":210}},"confusionMatrix":[{"actual":"bathroom-2","expected":"bathroom-2","count":166},{"expected":"deaf-2","count":189,"actual":"deaf-2"},{"actual":"hard-of-hearing-2","count":210,"expected":"hard-of-hearing-2"},{"count":108,"actual":"hello-2","expected":"hello-2"},{"expected":"hospital-2","count":93,"actual":"hospital-2"},{"count":176,"actual":"hospital-2","expected":"hurt-2"},{"count":200,"expected":"deaf-2","actual":"how-are-you-2"},{"expected":"hard-of-hearing-2","actual":"how-are-you-2","count":80},{"expected":"hospital-2","count":152,"actual":"how-are-you-2"},{"count":160,"actual":"hurt-2","expected":"hurt-2"},{"count":221,"actual":"please-2","expected":"please-2"},{"actual":"thank-you-2","expected":"thank-you-2","count":145}],"accuracy":0.68}},"progress":[{"tableIndex":0,"isLast":false,"currentRowIndex":0,"count":1,"tableDone":false,"acColumnHeader":{"trainingAccuracy":0.06423582136631012,"validationAccuracy":0.34631580114364624,"iterationCount":1,"hasValidation":true,"elapsedTime":0.118136},"percentComplete":0},{"percentComplete":0,"currentRowIndex":0,"isLast":false,"count":2,"tableIndex":0,"tableDone":false,"acColumnHeader":{"validationAccuracy":0.4873684346675873,"hasValidation":true,"iterationCount":2,"trainingAccuracy":0.4401713013648987,"elapsedTime":0.200555}},{"percentComplete":0,"currentRowIndex":0,"acColumnHeader":{"elapsedTime":0.278822,"trainingAccuracy":0.5325960516929626,"iterationCount":3,"validationAccuracy":0.535263180732727,"hasValidation":true},"tableIndex":0,"count":3,"tableDone":false,"isLast":false},{"percentComplete":0,"currentRowIndex":0,"acColumnHeader":{"iterationCount":4,"trainingAccuracy":0.5751289129257202,"validationAccuracy":0.640526294708252,"elapsedTime":0.353176,"hasValidation":true},"tableDone":false,"isLast":false,"tableIndex":0,"count":4},{"tableDone":false,"acColumnHeader":{"trainingAccuracy":0.6863046884536743,"elapsedTime":0.427841,"validationAccuracy":0.5915789604187012,"iterationCount":5,"hasValidation":true},"percentComplete":0,"currentRowIndex":0,"count":5,"tableIndex":0,"isLast":false},{"percentComplete":0,"currentRowIndex":0,"isLast":false,"tableDone":false,"tableIndex":0,"count":6,"acColumnHeader":{"hasValidation":true,"elapsedTime":0.552087,"iterationCount":6,"trainingAccuracy":0.7224346995353699,"validationAccuracy":0.6310526132583618}},{"acColumnHeader":{"iterationCount":10,"elapsedTime":0.876755,"trainingAccuracy":0.8492848873138428,"validationAccuracy":0.6800000071525574,"hasValidation":true},"percentComplete":0,"tableIndex":0,"currentRowIndex":0,"tableDone":true,"count":10,"isLast":false}],"startTime":"2024-03-04T19:37:34Z","trainingResults":{"activityClassifier":{"statsByLabel":{"hospital-2":{"count":3230,"precisionRecall":{"success":{"recall":1,"precision":0.9332562843108928}}},"bathroom-2":{"count":2294,"precisionRecall":{"success":{"precision":1,"recall":0.9864864864864865}}},"hurt-2":{"precisionRecall":{"success":{"recall":1,"precision":0.9695652173913043}},"count":2453},"how-are-you-2":{"precisionRecall":{"success":{"recall":1,"precision":0.9609226594301221}},"count":3541},"hard-of-hearing-2":{"precisionRecall":{"success":{"precision":1,"recall":0.999347045380346}},"count":3063},"please-2":{"precisionRecall":{"success":{"recall":0.9277717587576743,"precision":0.999222092570984}},"count":2769},"thank-you-2":{"count":2280,"precisionRecall":{"success":{"precision":1,"recall":0.9662280701754385}}},"hello-2":{"precisionRecall":{"success":{"precision":1,"recall":1}},"count":1789},"deaf-2":{"count":2633,"precisionRecall":{"success":{"precision":1,"recall":0.9453095328522598}}}},"confusionMatrix":[{"count":2263,"actual":"bathroom-2","expected":"bathroom-2"},{"count":31,"expected":"hospital-2","actual":"bathroom-2"},{"count":2489,"expected":"deaf-2","actual":"deaf-2"},{"expected":"how-are-you-2","count":144,"actual":"deaf-2"},{"actual":"hard-of-hearing-2","expected":"hard-of-hearing-2","count":3061},{"count":2,"expected":"please-2","actual":"hard-of-hearing-2"},{"count":1789,"actual":"hello-2","expected":"hello-2"},{"expected":"hospital-2","count":3230,"actual":"hospital-2"},{"expected":"how-are-you-2","actual":"how-are-you-2","count":3541},{"count":2453,"expected":"hurt-2","actual":"hurt-2"},{"actual":"please-2","expected":"hospital-2","count":200},{"expected":"please-2","actual":"please-2","count":2569},{"count":77,"expected":"hurt-2","actual":"thank-you-2"},{"count":2203,"actual":"thank-you-2","expected":"thank-you-2"}],"accuracy":0.9811242308331948}},"analysedDataType":"datasource","featureExtractionCheckpointMayBeAvailable":false,"finishTime":"2024-03-04T19:37:36Z","snapshottableCheckpoints":{"10":{"createdDate":"2024-03-04T19:37:36Z","modelURL":"file:\/\/\/Users\/simone\/Library\/Caches\/com.apple.dt.createml\/projects\/F94725CA-623E-4119-8056-4CFFB990C875845115d7072f729aadb86178db7cc96e350ca24c\/sessions\/checkpoint.sessions\/5B5047E9-1319-4A41-9E17-EFA6713EF8E5\/training-000000010.checkpoint.model\/checkpointModel.mlmodel","iteration":10}},"validationAccuracy":0.68},"modelEntity":{"createdDate":"2024-03-04T19:37:41Z","preferredFilename":"","modifiedDate":"2024-03-04T19:37:41Z","title":"","modelURL":"Snapshots\/Bad%20Iteration%2010.mlmodel\/","version":"1.0","id":"A29A23A9-AB8A-4781-9425-A8EAB40B9A94","experimentID":"5B5047E9-1319-4A41-9E17-EFA6713EF8E5"},"evaluationContainerEntity":{"id":"6f4c562b-7926-4f10-bc2c-97400316edcd","previewType":"activityClassifier","evaluationEntities":[],"trainingEvaluationEntity":{"id":"9b6cd58e-f43b-46ae-9ba7-4b729d3f7bb2","dataSourceID":"72F6BA12-E283-49A9-AE59-B059E1AC34C5","createdDate":"2024-03-04T19:37:41Z","dataResult":{"classesCount":9,"dataURL":"file:\/\/\/Users\/simone\/Documents\/Github\/capstone\/src\/Model\/Signs-V2\/train-data\/","dataAnalysis":{"classifierAnalysis":{"labelStats":{"hospital-2":30,"how-are-you-2":27,"hurt-2":29,"bathroom-2":25,"hello-2":24,"thank-you-2":31,"deaf-2":29,"hard-of-hearing-2":31,"please-2":23}},"summary":{"sampleCount":249,"canUseValidation":1,"classCount":9},"issues":[{"severity":"debug","description":"9 classes found, including thank-you-2, hard-of-hearing-2, hospital-2"},{"severity":"good","description":"249 activity recording files found, automatically creating validation set"},{"description":"Smallest class is \"please-2\" with 23 activity recording files","severity":"debug"},{"description":"Largest class is \"thank-you-2\" with 31 activity recording files","severity":"debug"},{"severity":"good","description":"6 features are selected"}]},"itemsCount":249,"dataSourceID":"72F6BA12-E283-49A9-AE59-B059E1AC34C5","createdDate":"2024-03-04T19:37:41Z"},"analysedDataType":"none"},"modifiedDate":"2024-03-04T21:03:45Z","testingEvaluationEntity":{"createdDate":"2024-03-04T19:37:41Z","id":"efd2dbea-d239-45ed-81e5-27fe1a4ebd17","dataResult":{"createdDate":"2024-03-04T19:37:41Z"},"analysedDataType":"none"},"createdDate":"2024-03-04T21:03:45Z","validationEvaluationEntity":{"analysedDataType":"datasource","dataResult":{"classesCount":9,"dataURL":"file:\/\/\/Users\/simone\/Documents\/Github\/capstone\/src\/Model\/Signs-V2\/eval-data\/","dataAnalysis":{"classifierAnalysis":{"labelStats":{"bathroom-2":2,"hurt-2":2,"hospital-2":2,"hard-of-hearing-2":2,"how-are-you-2":2,"deaf-2":2,"thank-you-2":2,"please-2":2,"hello-2":2}},"summary":{"classCount":9,"sampleCount":18,"canUseValidation":0},"issues":[{"description":"9 classes found, including bathroom-2, please-2, how-are-you-2","severity":"debug"},{"description":"Less than 100 total activity recording files found - add more to improve model validation","severity":"warning"},{"severity":"debug","description":"Smallest class is \"hello-2\" with 2 activity recording files"},{"severity":"debug","description":"Largest class is \"bathroom-2\" with 2 activity recording files"},{"severity":"good","description":"6 features are selected"}]},"itemsCount":18,"createdDate":"2024-03-04T19:37:41Z","dataSourceID":"36026F38-4019-4D1D-802B-B1B7EDC8D9F0"},"dataSourceID":"36026F38-4019-4D1D-802B-B1B7EDC8D9F0","id":"ba7feb37-7160-44d1-a51e-881473436c62","createdDate":"2024-03-04T19:37:41Z"}},"evaluationState":"uninitialized","version":"1.0","settingEntity":{"suggestedColumns":["accX","accY","accZ","gyroX","gyroY","gyroZ"],"algorithmType":"maxEnt","handActionClassifierAugmentations":[],"suggestedColumnValues":["0.03, 0.02, 0.02, 0.01, 0.01…","0.10, 0.10, 0.11, 0.14, 0.17…","-0.07, -0.09, -0.11, -0.13, -0.17…","0.21, 0.18, 0.03, -0.22, -0.52…","-0.09, -0.15, -0.23, -0.34, -0.50…","-0.01, -0.06, -0.13, -0.20, -0.29…"],"taskType":"activityClassifier","suggestedColumnTypes":["Double","Double","Double","Double","Double","Double"],"featureNames":["accX","accY","accZ","gyroX","gyroY","gyroZ"],"iterationCount":10,"harVideoAugmentations":0,"styleTransferAlgorithmType":"image","transferLearningEmbeddingType":"dynamic","seedType":"default","augmentations":[],"handPoseClassifierAugmentations":[]},"snapshotRole":{"snapshotParent":"5B5047E9-1319-4A41-9E17-EFA6713EF8E5","snapshotIteration":10},"title":"Iteration 10","activityEntities":["trainingDataAdded",[{"title":"Training Data Added","subtitle":"train-data","createdDate":"2024-03-04T19:37:27Z","id":"1566669E-6DE7-41BE-97E9-D19FD7373C5E","event":"trainingDataAdded"}],"validationDataAdded",[{"event":"validationDataAdded","createdDate":"2024-03-04T19:37:27Z","id":"0BBD98B7-B85B-4467-A1B9-E14E471EFBA7","title":"Validation Data Added","subtitle":"eval-data"}],"trainingFinished",[{"subtitle":"10 iterations","id":"7878B27F-06E0-454C-BF68-9901CE7AAB90","createdDate":"2024-03-04T19:37:36Z","event":"trainingFinished","title":"Training Completed"}],"trainingStarted",[{"title":"Training Started","event":"trainingStarted","subtitle":"10 iterations","id":"277F35DD-71A4-4232-A96E-4250569E993F","createdDate":"2024-03-04T19:37:34Z"}],"experimentCreated",[{"subtitle":"SigningInStyle 2","event":"experimentCreated","id":"B33CC095-3D96-48C4-A4D0-1CDFA69A754B","title":"Model Source Created","createdDate":"2024-03-04T19:36:54Z"}]],"createdDate":"2024-03-04T19:37:41Z","evaluationEntity":{"analysedDataType":"none","id":"b7232836-2356-48c1-adcc-786dcdb7d57f","dataResult":{}},"state":"trained","contentDataResult":{"createdDate":"2024-03-04T19:36:54Z"}}