{"modelEntity":{"modelURL":"Snapshots\/Wave%20Iteration%2010.mlmodel\/","experimentID":"47B7C0C4-DD7C-420B-82A6-D9A242BFACFD","preferredFilename":"","version":"1.0","id":"949E76C9-C1EA-4016-98B5-43FF43D05E42","modifiedDate":"2024-03-04T23:53:09Z","title":"","createdDate":"2024-03-04T23:53:09Z"},"title":"Iteration 10","version":"1.0","activityEntities":["trainingStarted",[{"subtitle":"10 iterations","title":"Training Started","id":"149DD89A-1506-4286-8DA7-46F60A36C899","createdDate":"2024-03-04T23:53:03Z","event":"trainingStarted"}],"validationDataAdded",[{"createdDate":"2024-03-04T23:52:55Z","title":"Validation Data Added","id":"C4DBD1E3-767F-4D7F-AAC9-56FE4EC6AC02","subtitle":"eval-data","event":"validationDataAdded"}],"trainingFinished",[{"id":"665A673F-B3EA-4E43-B3ED-0BB8B46EDCB3","title":"Training Completed","subtitle":"10 iterations","createdDate":"2024-03-04T23:53:05Z","event":"trainingFinished"}],"experimentCreated",[{"title":"Model Source Created","id":"573E7B28-A77A-4AFE-970F-4057DE1E4694","event":"experimentCreated","subtitle":"SigningInStyle 3","createdDate":"2024-03-04T23:52:30Z"}],"trainingDataAdded",[{"event":"trainingDataAdded","subtitle":"train-data","id":"44E97578-0EEA-4938-B3C3-1AF7BA9D78E3","createdDate":"2024-03-04T23:52:55Z","title":"Training Data Added"}]],"evaluationState":"uninitialized","validationEntity":{"dataSourceID":"6E470AF7-ACFD-425B-8E08-A5AC466A7805","dataResult":{"dataURL":"file:\/\/\/Users\/simone\/Documents\/Github\/capstone\/src\/Model\/Signs-V3\/eval-data\/","dataAnalysis":{"classifierAnalysis":{"labelStats":{"chocolate":2,"bad":2,"simone-does-the-wave":2,"hospital":2,"yes":2,"hard-of-hearing":2,"please":2,"thank-you":2,"deaf":2,"hurt":2,"how-are-you":2,"hello":2,"bathroom":2}},"summary":{"sampleCount":26,"classCount":13,"canUseValidation":0},"issues":[{"severity":"debug","description":"13 classes found, including hello, how-are-you, yes"},{"severity":"warning","description":"Less than 100 total activity recording files found - add more to improve model validation"},{"description":"Smallest class is \"thank-you\" with 2 activity recording files","severity":"debug"},{"severity":"debug","description":"Largest class is \"hello\" with 2 activity recording files"},{"description":"6 features are selected","severity":"good"}]},"createdDate":"2024-03-04T23:53:09Z","dataSourceID":"6E470AF7-ACFD-425B-8E08-A5AC466A7805","classesCount":13,"itemsCount":26},"analysedDataType":"datasource"},"settingEntity":{"algorithmType":"maxEnt","suggestedColumns":["accX","accY","accZ","gyroX","gyroY","gyroZ"],"handActionClassifierAugmentations":[],"taskType":"activityClassifier","suggestedColumnTypes":["Double","Double","Double","Double","Double","Double"],"suggestedColumnValues":["-0.01, 0.00, 0.01, 0.01, 0.00…","-0.01, -0.02, -0.01, 0.01, 0.00…","0.01, 0.00, -0.01, -0.00, 0.00…","-0.07, -0.05, -0.02, -0.02, -0.04…","-0.03, -0.04, -0.04, -0.02, -0.01…","0.00, -0.00, -0.00, -0.01, -0.00…"],"featureNames":["accX","accY","accZ","gyroX","gyroY","gyroZ"],"iterationCount":10,"harVideoAugmentations":0,"styleTransferAlgorithmType":"image","transferLearningEmbeddingType":"dynamic","seedType":"default","augmentations":[],"handPoseClassifierAugmentations":[],"predictionWindowSize":25},"createdDate":"2024-03-04T23:53:09Z","state":"trained","snapshotRole":{"snapshotIteration":10,"snapshotParent":"47B7C0C4-DD7C-420B-82A6-D9A242BFACFD"},"preferredFilename":"Wave Iteration 10","evaluationEntity":{"dataResult":{},"analysedDataType":"none","id":"1dcff502-91f3-4039-9f18-c05a853b128a"},"modifiedDate":"2024-03-05T00:03:34Z","id":"3DBFF436-E356-4E7E-AF1B-FFD82CD16FBF","trainingEntity":{"validationResults":{"activityClassifier":{"accuracy":0.6430921052631579,"statsByLabel":{"hard-of-hearing":{"precisionRecall":{"success":{"precision":0.8809523809523809,"recall":0.8809523809523809}},"count":210},"bad":{"precisionRecall":{"success":{"precision":0.8611111111111112,"recall":0.6739130434782609}},"count":230},"chocolate":{"count":338,"precisionRecall":{"success":{"recall":0.6301775147928994,"precision":0.5071428571428571}}},"bathroom":{"precisionRecall":{"success":{"precision":0.6527777777777778,"recall":0.8493975903614458}},"count":166},"yes":{"count":328,"precisionRecall":{"success":{"precision":0.9100719424460432,"recall":0.7713414634146342}}},"hospital":{"count":269,"precisionRecall":{"success":{"recall":0.5315985130111525,"precision":0.7771739130434783}}},"hurt":{"count":160,"precisionRecall":{"success":{"recall":1,"precision":0.5614035087719298}}},"thank-you":{"count":145,"precisionRecall":{"success":{"precision":0.7038834951456311,"recall":1}}},"hello":{"count":175,"precisionRecall":{"success":{"recall":0.5314285714285715,"precision":0.5535714285714286}}},"how-are-you":{"count":432,"precisionRecall":{"success":{"precision":0.9113475177304965,"recall":0.5949074074074074}}},"please":{"precisionRecall":{"success":{"recall":0.4343891402714932,"precision":0.5614035087719298}},"count":221},"deaf":{"precisionRecall":{"success":{"recall":0.4708994708994709,"precision":0.4158878504672897}},"count":189},"simone-does-the-wave":{"precisionRecall":{"success":{"precision":0.11061946902654868,"recall":0.14124293785310735}},"count":177}},"confusionMatrix":[{"expected":"bad","count":155,"actual":"bad"},{"expected":"bathroom","count":25,"actual":"bad"},{"count":25,"actual":"bad","expected":"chocolate"},{"actual":"bad","count":25,"expected":"hurt"},{"actual":"bathroom","count":141,"expected":"bathroom"},{"actual":"bathroom","expected":"how-are-you","count":25},{"actual":"chocolate","count":213,"expected":"chocolate"},{"expected":"please","actual":"chocolate","count":75},{"count":50,"actual":"chocolate","expected":"simone-does-the-wave"},{"expected":"bathroom","actual":"deaf","count":25},{"count":89,"actual":"deaf","expected":"deaf"},{"expected":"simone-does-the-wave","actual":"deaf","count":75},{"actual":"hard-of-hearing","expected":"deaf","count":25},{"actual":"hard-of-hearing","expected":"hard-of-hearing","count":185},{"actual":"hello","expected":"bad","count":25},{"count":57,"expected":"chocolate","actual":"hello"},{"actual":"hello","expected":"hello","count":93},{"actual":"hospital","expected":"hospital","count":143},{"actual":"hospital","expected":"hurt","count":100},{"expected":"simone-does-the-wave","count":26,"actual":"hospital"},{"expected":"chocolate","actual":"how-are-you","count":25},{"count":100,"actual":"how-are-you","expected":"deaf"},{"count":257,"actual":"how-are-you","expected":"how-are-you"},{"actual":"how-are-you","expected":"simone-does-the-wave","count":50},{"expected":"hurt","count":160,"actual":"hurt"},{"count":25,"actual":"please","expected":"chocolate"},{"actual":"please","expected":"hard-of-hearing","count":25},{"actual":"please","expected":"hello","count":75},{"expected":"please","count":96,"actual":"please"},{"expected":"bathroom","actual":"simone-does-the-wave","count":25},{"expected":"hospital","count":41,"actual":"simone-does-the-wave"},{"expected":"simone-does-the-wave","actual":"simone-does-the-wave","count":25},{"expected":"thank-you","actual":"simone-does-the-wave","count":61},{"actual":"simone-does-the-wave","expected":"yes","count":25},{"expected":"thank-you","count":145,"actual":"thank-you"},{"count":75,"actual":"yes","expected":"chocolate"},{"actual":"yes","expected":"yes","count":253}]}},"resumableCheckpoint":{"iteration":10,"createdDate":"2024-03-04T23:53:05Z","checkpointURL":"file:\/\/\/Users\/simone\/Library\/Caches\/com.apple.dt.createml\/projects\/F94725CA-623E-4119-8056-4CFFB990C875845115d7072f729aadb86178db7cc96e350ca24c\/sessions\/checkpoint.sessions\/47B7C0C4-DD7C-420B-82A6-D9A242BFACFD\/training-000000010.checkpoint"},"startTime":"2024-03-04T23:53:03Z","dataResult":{"createdDate":"2024-03-04T23:53:09Z","dataURL":"file:\/\/\/Users\/simone\/Documents\/Github\/capstone\/src\/Model\/Signs-V3\/train-data\/","classesCount":13,"columnValues":["-0.01, 0.00, 0.01, 0.01, 0.00…","-0.01, -0.02, -0.01, 0.01, 0.00…","0.01, 0.00, -0.01, -0.00, 0.00…","-0.07, -0.05, -0.02, -0.02, -0.04…","-0.03, -0.04, -0.04, -0.02, -0.01…","0.00, -0.00, -0.00, -0.01, -0.00…"],"itemsCount":320,"dataAnalysis":{"summary":{"canUseValidation":1,"classCount":13,"sampleCount":320},"classifierAnalysis":{"labelStats":{"thank-you":31,"hurt":29,"deaf":29,"bad":11,"please":23,"hello":22,"hospital":30,"hard-of-hearing":31,"how-are-you":27,"chocolate":13,"bathroom":25,"yes":18,"simone-does-the-wave":31}},"issues":[{"severity":"debug","description":"13 classes found, including hard-of-hearing, simone-does-the-wave, thank-you"},{"severity":"good","description":"320 activity recording files found, automatically creating validation set"},{"description":"Smallest class is \"bad\" with 11 activity recording files","severity":"debug"},{"description":"Largest class is \"hard-of-hearing\" with 31 activity recording files","severity":"debug"},{"description":"6 features are selected","severity":"good"}]},"columns":["accX","accY","accZ","gyroX","gyroY","gyroZ"],"dataSourceID":"5132782F-E7CE-4FCE-AB6F-066909475967","columnTypes":["Double","Double","Double","Double","Double","Double"]},"finishTime":"2024-03-04T23:53:05Z","analysedDataType":"datasource","featureExtractionCheckpointMayBeAvailable":false,"checkpointMetrics":{"10":{"iteration":10,"createdDate":"2024-03-04T23:53:05Z","metrics":{"validationAccuracy":0.6430920958518982,"accuracy":0.5993972420692444,"validationLoss":0,"loss":0.2966867685317993}}},"trainingResults":{"activityClassifier":{"accuracy":0.8475173072332299,"confusionMatrix":[{"count":1130,"actual":"bad","expected":"bad"},{"actual":"bad","expected":"chocolate","count":150},{"count":100,"expected":"thank-you","actual":"bad"},{"expected":"bathroom","actual":"bathroom","count":2163},{"count":50,"actual":"bathroom","expected":"chocolate"},{"expected":"deaf","count":31,"actual":"bathroom"},{"count":50,"actual":"bathroom","expected":"thank-you"},{"expected":"chocolate","actual":"chocolate","count":1855},{"expected":"deaf","actual":"chocolate","count":25},{"expected":"hello","count":50,"actual":"chocolate"},{"count":50,"expected":"hospital","actual":"chocolate"},{"count":25,"actual":"chocolate","expected":"hurt"},{"count":120,"actual":"chocolate","expected":"simone-does-the-wave"},{"count":25,"expected":"yes","actual":"chocolate"},{"count":25,"expected":"bathroom","actual":"deaf"},{"actual":"deaf","expected":"deaf","count":2294},{"expected":"hard-of-hearing","count":75,"actual":"deaf"},{"count":239,"actual":"deaf","expected":"simone-does-the-wave"},{"actual":"hard-of-hearing","expected":"bad","count":50},{"expected":"bathroom","actual":"hard-of-hearing","count":100},{"expected":"chocolate","count":1,"actual":"hard-of-hearing"},{"expected":"deaf","count":100,"actual":"hard-of-hearing"},{"actual":"hard-of-hearing","expected":"hard-of-hearing","count":2638},{"actual":"hard-of-hearing","expected":"hello","count":150},{"actual":"hard-of-hearing","expected":"hospital","count":24},{"count":25,"actual":"hello","expected":"bad"},{"expected":"chocolate","actual":"hello","count":175},{"expected":"hard-of-hearing","actual":"hello","count":72},{"expected":"hello","count":1177,"actual":"hello"},{"actual":"hello","expected":"simone-does-the-wave","count":13},{"expected":"yes","actual":"hello","count":25},{"count":50,"actual":"hospital","expected":"chocolate"},{"actual":"hospital","expected":"hospital","count":3105},{"count":25,"actual":"hospital","expected":"simone-does-the-wave"},{"expected":"thank-you","count":50,"actual":"hospital"},{"expected":"chocolate","count":25,"actual":"how-are-you"},{"expected":"deaf","actual":"how-are-you","count":50},{"actual":"how-are-you","expected":"how-are-you","count":3391},{"actual":"how-are-you","count":50,"expected":"simone-does-the-wave"},{"expected":"yes","actual":"how-are-you","count":25},{"actual":"hurt","count":47,"expected":"deaf"},{"count":75,"expected":"hospital","actual":"hurt"},{"actual":"hurt","count":2127,"expected":"hurt"},{"actual":"hurt","expected":"please","count":75},{"count":54,"actual":"hurt","expected":"simone-does-the-wave"},{"expected":"yes","count":75,"actual":"hurt"},{"actual":"please","expected":"chocolate","count":104},{"actual":"please","count":75,"expected":"hard-of-hearing"},{"expected":"hello","count":500,"actual":"please"},{"count":25,"actual":"please","expected":"how-are-you"},{"actual":"please","expected":"hurt","count":50},{"actual":"please","expected":"please","count":1965},{"expected":"simone-does-the-wave","actual":"please","count":25},{"expected":"thank-you","count":25,"actual":"please"},{"expected":"bad","actual":"simone-does-the-wave","count":131},{"actual":"simone-does-the-wave","expected":"bathroom","count":86},{"expected":"chocolate","actual":"simone-does-the-wave","count":240},{"count":134,"actual":"simone-does-the-wave","expected":"deaf"},{"expected":"hard-of-hearing","actual":"simone-does-the-wave","count":125},{"count":51,"expected":"hello","actual":"simone-does-the-wave"},{"count":80,"actual":"simone-does-the-wave","expected":"hospital"},{"actual":"simone-does-the-wave","expected":"how-are-you","count":284},{"expected":"hurt","count":167,"actual":"simone-does-the-wave"},{"count":103,"expected":"please","actual":"simone-does-the-wave"},{"actual":"simone-does-the-wave","expected":"simone-does-the-wave","count":2374},{"count":50,"actual":"thank-you","expected":"chocolate"},{"actual":"thank-you","count":25,"expected":"deaf"},{"actual":"thank-you","expected":"hurt","count":100},{"expected":"thank-you","count":2053,"actual":"thank-you"},{"expected":"yes","actual":"thank-you","count":52},{"count":227,"expected":"chocolate","actual":"yes"},{"actual":"yes","expected":"deaf","count":25},{"expected":"hospital","actual":"yes","count":50},{"count":25,"actual":"yes","expected":"thank-you"},{"expected":"yes","actual":"yes","count":2130}],"statsByLabel":{"yes":{"count":2457,"precisionRecall":{"success":{"precision":0.9133790737564322,"recall":0.8669108669108669}}},"bad":{"count":1380,"precisionRecall":{"success":{"recall":0.8188405797101449,"precision":0.8458083832335329}}},"hello":{"precisionRecall":{"success":{"precision":0.6104771784232366,"recall":0.7915265635507733}},"count":1487},"simone-does-the-wave":{"precisionRecall":{"success":{"precision":0.8186206896551724,"recall":0.6288741721854305}},"count":3775},"how-are-you":{"precisionRecall":{"success":{"precision":0.9164864864864865,"recall":0.9576390850042361}},"count":3541},"bathroom":{"precisionRecall":{"success":{"precision":0.9111204717775906,"recall":0.9428945074106364}},"count":2294},"hurt":{"count":2453,"precisionRecall":{"success":{"precision":0.8614823815309842,"recall":0.8671015083571137}}},"please":{"precisionRecall":{"success":{"precision":0.9169388707419506,"recall":0.7096424702058505}},"count":2769},"chocolate":{"precisionRecall":{"success":{"recall":0.8627906976744186,"precision":0.6337546976426375}},"count":2150},"deaf":{"precisionRecall":{"success":{"precision":0.8399853533504211,"recall":0.8712495252563616}},"count":2633},"hard-of-hearing":{"count":3063,"precisionRecall":{"success":{"precision":0.8837520938023451,"recall":0.861247143323539}}},"thank-you":{"precisionRecall":{"success":{"precision":0.8914459400781589,"recall":0.900438596491228}},"count":2280},"hospital":{"precisionRecall":{"success":{"precision":0.9175531914893617,"recall":0.9613003095975232}},"count":3230}}}},"trainingAccuracy":0.8475173072332299,"snapshottableCheckpoints":{"10":{"modelURL":"file:\/\/\/Users\/simone\/Library\/Caches\/com.apple.dt.createml\/projects\/F94725CA-623E-4119-8056-4CFFB990C875845115d7072f729aadb86178db7cc96e350ca24c\/sessions\/checkpoint.sessions\/47B7C0C4-DD7C-420B-82A6-D9A242BFACFD\/training-000000010.checkpoint.model\/checkpointModel.mlmodel","iteration":10,"createdDate":"2024-03-04T23:53:05Z"}},"progress":[{"isLast":false,"count":1,"tableIndex":0,"currentRowIndex":0,"tableDone":false,"acColumnHeader":{"elapsedTime":0.11146,"trainingAccuracy":0.0509369783103466,"validationAccuracy":0.10888157784938812,"iterationCount":1,"hasValidation":true},"percentComplete":0},{"tableDone":false,"acColumnHeader":{"trainingAccuracy":0.19055861234664917,"validationAccuracy":0.2858552634716034,"iterationCount":2,"hasValidation":true,"elapsedTime":0.177537},"percentComplete":0,"currentRowIndex":0,"count":2,"tableIndex":0,"isLast":false},{"percentComplete":0,"currentRowIndex":0,"acColumnHeader":{"elapsedTime":0.254526,"iterationCount":3,"trainingAccuracy":0.25933992862701416,"hasValidation":true,"validationAccuracy":0.46973684430122375},"tableDone":false,"isLast":false,"tableIndex":0,"count":3},{"percentComplete":0,"currentRowIndex":0,"acColumnHeader":{"hasValidation":true,"iterationCount":4,"validationAccuracy":0.539802610874176,"elapsedTime":0.317114,"trainingAccuracy":0.3206911087036133},"tableIndex":0,"isLast":false,"tableDone":false,"count":4},{"tableIndex":0,"isLast":false,"currentRowIndex":0,"tableDone":false,"count":5,"acColumnHeader":{"validationAccuracy":0.589802622795105,"iterationCount":5,"elapsedTime":0.379941,"trainingAccuracy":0.3997374176979065,"hasValidation":true},"percentComplete":0},{"percentComplete":0,"isLast":false,"currentRowIndex":0,"tableDone":false,"tableIndex":0,"count":6,"acColumnHeader":{"hasValidation":true,"iterationCount":6,"trainingAccuracy":0.459805428981781,"elapsedTime":0.443378,"validationAccuracy":0.5960526466369629}},{"acColumnHeader":{"elapsedTime":0.690054,"validationAccuracy":0.6430920958518982,"trainingAccuracy":0.5993972420692444,"iterationCount":10,"hasValidation":true},"currentRowIndex":0,"tableDone":true,"isLast":false,"percentComplete":0,"count":10,"tableIndex":0}],"dataSourceID":"5132782F-E7CE-4FCE-AB6F-066909475967","validationAccuracy":0.6430921052631579},"evaluationContainerEntity":{"createdDate":"2024-03-05T00:03:34Z","validationEvaluationEntity":{"id":"de9d59d6-eaf2-4907-a927-573373ca4d1b","dataResult":{"classesCount":13,"dataAnalysis":{"summary":{"sampleCount":26,"classCount":13,"canUseValidation":0},"issues":[{"severity":"debug","description":"13 classes found, including hello, how-are-you, yes"},{"description":"Less than 100 total activity recording files found - add more to improve model validation","severity":"warning"},{"description":"Smallest class is \"thank-you\" with 2 activity recording files","severity":"debug"},{"severity":"debug","description":"Largest class is \"hello\" with 2 activity recording files"},{"severity":"good","description":"6 features are selected"}],"classifierAnalysis":{"labelStats":{"hard-of-hearing":2,"deaf":2,"how-are-you":2,"hurt":2,"bad":2,"chocolate":2,"simone-does-the-wave":2,"please":2,"hospital":2,"thank-you":2,"yes":2,"bathroom":2,"hello":2}}},"createdDate":"2024-03-04T23:53:09Z","itemsCount":26,"dataSourceID":"6E470AF7-ACFD-425B-8E08-A5AC466A7805","dataURL":"file:\/\/\/Users\/simone\/Documents\/Github\/capstone\/src\/Model\/Signs-V3\/eval-data\/"},"createdDate":"2024-03-04T23:53:09Z","analysedDataType":"datasource","dataSourceID":"6E470AF7-ACFD-425B-8E08-A5AC466A7805"},"evaluationEntities":[],"modifiedDate":"2024-03-05T00:03:34Z","trainingEvaluationEntity":{"id":"2ab7de97-f114-44d0-9edb-f03752b1ef54","analysedDataType":"none","dataSourceID":"5132782F-E7CE-4FCE-AB6F-066909475967","createdDate":"2024-03-04T23:53:09Z","dataResult":{"dataAnalysis":{"issues":[{"severity":"debug","description":"13 classes found, including hard-of-hearing, simone-does-the-wave, thank-you"},{"severity":"good","description":"320 activity recording files found, automatically creating validation set"},{"description":"Smallest class is \"bad\" with 11 activity recording files","severity":"debug"},{"description":"Largest class is \"hard-of-hearing\" with 31 activity recording files","severity":"debug"},{"severity":"good","description":"6 features are selected"}],"classifierAnalysis":{"labelStats":{"deaf":29,"please":23,"bathroom":25,"chocolate":13,"thank-you":31,"how-are-you":27,"hello":22,"hospital":30,"yes":18,"hard-of-hearing":31,"simone-does-the-wave":31,"hurt":29,"bad":11}},"summary":{"classCount":13,"canUseValidation":1,"sampleCount":320}},"classesCount":13,"createdDate":"2024-03-04T23:53:09Z","dataSourceID":"5132782F-E7CE-4FCE-AB6F-066909475967","dataURL":"file:\/\/\/Users\/simone\/Documents\/Github\/capstone\/src\/Model\/Signs-V3\/train-data\/","itemsCount":320}},"previewType":"activityClassifier","testingEvaluationEntity":{"dataResult":{"createdDate":"2024-03-04T23:53:09Z"},"analysedDataType":"none","createdDate":"2024-03-04T23:53:09Z","id":"7952dd60-dc02-444f-9b1e-900196905704"},"id":"f8f58e0a-7c6f-4587-af6e-a94c556ff2f2"},"contentDataResult":{"createdDate":"2024-03-04T23:52:30Z"}}